pywebfaction-0.1.1.dist-info/DESCRIPTION.rst
pywebfaction-0.1.1.dist-info/pydist.json
pywebfaction-0.1.1.dist-info/entry_points.txt
pywebfaction-0.1.1.dist-info/top_level.txt
pywebfaction-0.1.1.dist-info/RECORD
pywebfaction-0.1.1.dist-info/WHEEL
pywebfaction-0.1.1.dist-info/METADATA
pywebfaction/utils.py
pywebfaction/cli.py
pywebfaction/exceptions.py
pywebfaction/mailbox_name.py
pywebfaction/__init__.py
pywebfaction-0.1.1.data/scripts/pywebfaction
