Metadata-Version: 2.0
Name: pywebfaction
Version: 0.1.1
Summary: A tool for interacting with the WebFaction API.
Home-page: https://github.com/dominicrodger/pywebfaction
Author: Dominic Rodger
Author-email: dominicrodger@gmail.com
License: BSD
Keywords: pywebfaction
Platform: UNKNOWN
Classifier: Development Status :: 2 - Pre-Alpha
Classifier: Intended Audience :: Developers
Classifier: License :: OSI Approved :: BSD License
Classifier: Natural Language :: English
Classifier: Programming Language :: Python :: 2
Classifier: Programming Language :: Python :: 2.7
Classifier: Programming Language :: Python :: 3
Classifier: Programming Language :: Python :: 3.3
Requires-Dist: six (>=1.5.0)
Requires-Dist: tabulate
Requires-Dist: docopt
